shapelink/__init__.py
shapelink/_version.py
shapelink/_version_save.py
shapelink/cli.py
shapelink/msg_def.py
shapelink/shapein_simulator.py
shapelink/shapelink_plugin.py
shapelink/util.py
shapelink-0.1.1.dist-info/LICENSE
shapelink-0.1.1.dist-info/METADATA
shapelink-0.1.1.dist-info/WHEEL
shapelink-0.1.1.dist-info/entry_points.txt
shapelink-0.1.1.dist-info/top_level.txt
shapelink-0.1.1.dist-info/RECORD
