Metadata-Version: 2.1
Name: shapelink
Version: 0.1.1
Summary: Inter-process communication with Shape-In
Home-page: https://github.com/ZELLMECHANIK-DRESDEN/shapelink
Author: Paul Müller
Author-email: dev@craban.de
License: GPL v3
Keywords: fcs,flow cytometry,flow cytometry standard
Platform: ALL
Classifier: Operating System :: OS Independent
Classifier: Programming Language :: Python :: 3
Classifier: Topic :: Scientific/Engineering :: Visualization
Classifier: Intended Audience :: Science/Research
Requires-Python: >=3.6
Requires-Dist: click (>=7)
Requires-Dist: dclab (>0.32.2)
Requires-Dist: numpy (>=1.7.0)
Requires-Dist: PySide2
Requires-Dist: pyzmq
